kof_api/Alchemist.py
kof_api/Animal.py
kof_api/AuxiliaryScutum.py
kof_api/Bandit.py
kof_api/Blacksmith.py
kof_api/Bludgeon.py
kof_api/Brigantine.py
kof_api/BronzeLSword.py
kof_api/BronzeLamellar.py
kof_api/BronzeSSword.py
kof_api/Building.py
kof_api/Butcher.py
kof_api/Camel.py
kof_api/Caraval.py
kof_api/CenturionGladius.py
kof_api/Chestplate.py
kof_api/Chicken.py
kof_api/City.py
kof_api/Club.py
kof_api/Cog.py
kof_api/Cow.py
kof_api/Donkey.py
kof_api/Enemy.py
kof_api/Farmer.py
kof_api/Fluyt.py
kof_api/Galley.py
kof_api/Hauberk.py
kof_api/Helmet.py
kof_api/Horse.py
kof_api/IronFlail.py
kof_api/IronLSword.py
kof_api/IronLamellar.py
kof_api/IronMace.py
kof_api/IronSSword.py
kof_api/Item.py
kof_api/Jazerant.py
kof_api/Kettle_Hat.py
kof_api/Kiritsuke.py
kof_api/LeatherLamellar.py
kof_api/LegionaryScutum.py
kof_api/Longship.py
kof_api/LoricaHamata.py
kof_api/Math.py
kof_api/Merchant.py
kof_api/MerchantGalleon.py
kof_api/MorningStar.py
kof_api/NPC.py
kof_api/Names.py
kof_api/Pig.py
kof_api/Player.py
kof_api/Region.py
kof_api/Shield.py
kof_api/Ship.py
kof_api/Sloop.py
kof_api/Spangenhelm.py
kof_api/StableMaster.py
kof_api/Sword.py
kof_api/Thief.py
kof_api/WarCaraval.py
kof_api/WarFluyt.py
kof_api/WarGalleon.py
kof_api/WarGalley.py
kof_api/WarmongerBarbSword.py
kof_api/WoolGambeson.py
kof_api/__init__.py
kof_api-0.0.8.dist-info/METADATA
kof_api-0.0.8.dist-info/WHEEL
kof_api-0.0.8.dist-info/top_level.txt
kof_api-0.0.8.dist-info/RECORD
