Metadata-Version: 2.1
Name: kof-api
Version: 0.0.8
Summary: API for Kingdoms of Fortune.
Home-page: UNKNOWN
Author: GalaxyIndieDev
Author-email: <zachnichelson304@gmail.com>
License: UNKNOWN
Keywords: python,api,kof,video game
Platform: UNKNOWN
Classifier: Development Status :: 1 - Planning
Classifier: Intended Audience :: Developers
Classifier: Programming Language :: Python :: 3
Classifier: Operating System :: Microsoft :: Windows
